{"modules":[{"assertions":{},"code":"\"use strict\";\r\nclass Index extends ViewPU {\r\n    constructor(parent, params, __localStorage, elmtId = -1) {\r\n        super(parent, __localStorage, elmtId);\r\n        this.__message = new ObservedPropertySimplePU('Hello World', this, \"message\");\r\n        this.setInitiallyProvidedValue(params);\r\n    }\r\n    setInitiallyProvidedValue(params) {\r\n        if (params.message !== undefined) {\r\n            this.message = params.message;\r\n        }\r\n    }\r\n    updateStateVars(params) {\r\n    }\r\n    purgeVariableDependenciesOnElmtId(rmElmtId) {\r\n        this.__message.purgeDependencyOnElmtId(rmElmtId);\r\n    }\r\n    aboutToBeDeleted() {\r\n        this.__message.aboutToBeDeleted();\r\n        SubscriberManager.Get().delete(this.id__());\r\n        this.aboutToBeDeletedInternal();\r\n    }\r\n    get message() {\r\n        return this.__message.get();\r\n    }\r\n    set message(newValue) {\r\n        this.__message.set(newValue);\r\n    }\r\n    initialRender() {\r\n        this.observeComponentCreation((elmtId, isInitialRender) => {\r\n            ViewStackProcessor.StartGetAccessRecordingFor(elmtId);\r\n            Row.create();\r\n            Row.height('100%');\r\n            if (!isInitialRender) {\r\n                Row.pop();\r\n            }\r\n            ViewStackProcessor.StopGetAccessRecording();\r\n        });\r\n        this.observeComponentCreation((elmtId, isInitialRender) => {\r\n            ViewStackProcessor.StartGetAccessRecordingFor(elmtId);\r\n            Column.create();\r\n            Column.width('100%');\r\n            if (!isInitialRender) {\r\n                Column.pop();\r\n            }\r\n            ViewStackProcessor.StopGetAccessRecording();\r\n        });\r\n        this.observeComponentCreation((elmtId, isInitialRender) => {\r\n            ViewStackProcessor.StartGetAccessRecordingFor(elmtId);\r\n            Text.create(this.message);\r\n            Text.fontSize(50);\r\n            Text.fontWeight(FontWeight.Bold);\r\n            Text.fontColor('#36D');\r\n            Text.onClick(() => {\r\n                this.message = 'Hello ArkTS!';\r\n            });\r\n            if (!isInitialRender) {\r\n                Text.pop();\r\n            }\r\n            ViewStackProcessor.StopGetAccessRecording();\r\n        });\r\n        Text.pop();\r\n        this.observeComponentCreation((elmtId, isInitialRender) => {\r\n            ViewStackProcessor.StartGetAccessRecordingFor(elmtId);\r\n            Image.create('https://res.vmallres.com/pimages//uomcdn/CN/pms/202305/gbom/6942103102790/group//428_428_B5CF48BC9E98F629F44ED8DF4F70EB86.png');\r\n            Image.width(250);\r\n            if (!isInitialRender) {\r\n                Image.pop();\r\n            }\r\n            ViewStackProcessor.StopGetAccessRecording();\r\n        });\r\n        Column.pop();\r\n        Row.pop();\r\n    }\r\n    rerender() {\r\n        this.updateDirtyElements();\r\n    }\r\n}\r\nViewStackProcessor.StartGetAccessRecordingFor(ViewStackProcessor.AllocateNewElmetIdForNextComponent());\r\nloadDocument(new Index(undefined, {}));\r\nViewStackProcessor.StopGetAccessRecording();\r\n//# sourceMappingURL=Index.js.map","customTransformCache":false,"dependencies":[],"id":"/Users/ziyounian/DevEcoStudioProjects/MyApplication/entry/src/main/ets/pages/Index.ets","meta":{"hostModulesInfo":[],"moduleName":"entry","isLocalDependency":true,"isNodeEntryFile":false,"pkgPath":"/Users/ziyounian/DevEcoStudioProjects/MyApplication/entry"},"moduleSideEffects":true,"originalCode":"@Entry\n@Component\nstruct Index {\n  @State message: string = 'Hello World'\n\n  build() {\n    Row() {\n      Column() {\n        Text(this.message)\n          .fontSize(50)\n          .fontWeight(FontWeight.Bold)\n          .fontColor('#36D')\n          .onClick(() => {\n            this.message = 'Hello ArkTS!'\n          })\n\n        Image('https://res.vmallres.com/pimages//uomcdn/CN/pms/202305/gbom/6942103102790/group//428_428_B5CF48BC9E98F629F44ED8DF4F70EB86.png')\n          .width(250)\n      }\n      .width('100%')\n    }\n    .height('100%')\n  }\n}","originalSourcemap":{"version":3,"mappings":[[],[[6,0,2,7],[7,0,2,12],[8,0,2,12],[9,0,2,12],[10,0,2,12],[11,0,2,12],[12,0,2,12],[13,0,2,12],[14,0,2,12],[15,0,2,12],[16,0,2,12],[17,0,2,12],[18,0,2,12],[19,0,2,12],[20,0,2,12],[21,0,2,12],[22,0,2,12],[23,0,2,12],[24,0,2,12],[25,0,2,12],[26,0,2,12],[27,0,2,12],[28,0,2,12],[29,0,2,12]],[[0,0,0,0],[1,0,0,0],[2,0,0,0],[3,0,0,0],[4,0,0,0],[5,0,0,0],[6,0,0,0],[7,0,0,0],[8,0,0,0],[9,0,0,0],[10,0,0,0],[11,0,0,0],[12,0,0,0],[13,0,0,0],[14,0,0,0],[15,0,0,0],[16,0,0,0],[17,0,0,0],[18,0,0,0],[19,0,0,0],[20,0,0,0],[21,0,0,0],[22,0,0,0],[23,0,0,0],[24,0,0,0],[25,0,0,0],[26,0,0,0],[27,0,0,0],[28,0,0,0],[29,0,0,0],[30,0,0,0],[31,0,0,0],[32,0,0,0],[33,0,0,0],[34,0,0,0],[35,0,0,0],[36,0,0,0],[37,0,0,0],[38,0,0,0],[39,0,0,0],[40,0,0,0],[41,0,0,0],[42,0,0,0],[43,0,0,0],[44,0,0,0],[45,0,0,0],[46,0,0,0],[47,0,0,0],[48,0,0,0],[49,0,0,0],[50,0,0,0],[51,0,0,0],[52,0,0,0],[53,0,0,0],[54,0,0,0],[55,0,0,0],[56,0,0,0],[57,0,0,0],[58,0,0,0],[59,0,0,0],[60,0,0,0],[61,0,0,0],[62,0,0,0],[63,0,0,0]],[],[[54,0,3,27],[55,0,3,40],[56,0,3,40],[57,0,3,40],[58,0,3,40],[59,0,3,40],[60,0,3,40],[61,0,3,40],[62,0,3,40],[63,0,3,40],[64,0,3,40],[65,0,3,40],[66,0,3,40],[67,0,3,40],[68,0,3,40],[69,0,3,40],[70,0,3,40],[71,0,3,40],[72,0,3,40],[73,0,3,40],[74,0,3,40],[75,0,3,40],[76,0,3,40],[77,0,3,40],[78,0,3,40],[79,0,3,40],[80,0,3,40],[81,0,3,40],[82,0,3,40],[83,0,3,40],[84,0,3,40],[85,0,3,40],[86,0,3,40],[87,0,3,40]],[],[[0,0,0,0],[1,0,0,0],[2,0,0,0],[3,0,0,0],[4,0,0,0],[5,0,0,0],[6,0,0,0]],[],[],[],[],[],[],[],[],[],[],[],[],[],[],[],[[8,0,3,9],[9,0,3,16],[10,0,3,16],[11,0,3,16],[12,0,3,16],[13,0,3,16],[14,0,3,16],[15,0,3,16],[16,0,3,16],[17,0,3,16],[18,0,3,16],[19,0,3,16],[20,0,3,16]],[],[],[[8,0,3,9],[9,0,3,16],[10,0,3,16],[11,0,3,16],[12,0,3,16],[13,0,3,16],[14,0,3,16],[15,0,3,16],[16,0,3,16],[17,0,3,16],[18,0,3,16],[19,0,3,16],[20,0,3,16],[21,0,3,16],[22,0,3,16],[23,0,3,16],[24,0,3,16],[25,0,3,16],[26,0,3,16],[27,0,3,16],[28,0,3,16]],[],[],[[0,0,5,2],[1,0,5,2],[2,0,5,2],[3,0,5,2],[4,0,5,2],[5,0,5,2],[6,0,5,2],[7,0,5,2],[8,0,5,2],[9,0,5,2],[10,0,5,2],[11,0,5,2],[12,0,5,2],[13,0,5,2],[14,0,5,2],[15,0,5,2],[16,0,5,2],[17,0,5,2],[18,0,5,2],[19,0,5,2],[20,0,5,2],[21,0,5,2],[22,0,5,2]],[],[],[[12,0,6,4],[13,0,6,7],[14,0,6,7],[15,0,6,7],[16,0,6,7],[17,0,6,7],[18,0,6,7],[19,0,6,7],[20,0,6,7],[21,0,6,7],[22,0,6,7],[23,0,6,7],[24,0,6,7],[25,0,6,7],[26,0,6,7]],[[12,0,6,4],[13,0,6,7],[14,0,6,7],[15,0,6,7],[16,0,21,5],[17,0,21,11],[18,0,21,11],[19,0,21,11],[20,0,21,11],[21,0,21,11],[22,0,21,11],[23,0,21,12],[24,0,21,18],[25,0,21,18],[26,0,21,18],[27,0,21,18],[28,0,21,18],[29,0,21,18],[30,0,21,18],[31,0,21,18],[32,0,21,18]],[],[[16,0,6,4],[17,0,6,7],[18,0,6,7],[19,0,6,7],[20,0,6,7],[21,0,6,7],[22,0,6,7],[23,0,6,7],[24,0,6,7],[25,0,6,7],[26,0,6,7],[27,0,6,7]],[],[],[],[],[],[[12,0,7,6],[13,0,7,12],[14,0,7,12],[15,0,7,12],[16,0,7,12],[17,0,7,12],[18,0,7,12],[19,0,7,12],[20,0,7,12],[21,0,7,12],[22,0,7,12],[23,0,7,12],[24,0,7,12],[25,0,7,12],[26,0,7,12],[27,0,7,12],[28,0,7,12],[29,0,7,12]],[[12,0,7,6],[13,0,7,12],[14,0,7,12],[15,0,7,12],[16,0,7,12],[17,0,7,12],[18,0,7,12],[19,0,19,7],[20,0,19,12],[21,0,19,12],[22,0,19,12],[23,0,19,12],[24,0,19,12],[25,0,19,13],[26,0,19,19],[27,0,19,19],[28,0,19,19],[29,0,19,19],[30,0,19,19],[31,0,19,19],[32,0,19,19],[33,0,19,19],[34,0,19,19]],[],[[16,0,7,6],[17,0,7,12],[18,0,7,12],[19,0,7,12],[20,0,7,12],[21,0,7,12],[22,0,7,12],[23,0,7,12],[24,0,7,12],[25,0,7,12],[26,0,7,12],[27,0,7,12],[28,0,7,12],[29,0,7,12],[30,0,7,12]],[],[],[],[],[],[[12,0,8,8],[13,0,8,12],[14,0,8,12],[15,0,8,12],[16,0,8,12],[17,0,8,12],[18,0,8,12],[19,0,8,12],[20,0,8,12],[21,0,8,12],[22,0,8,12],[23,0,8,12],[24,0,8,13],[25,0,8,17],[26,0,8,17],[27,0,8,17],[28,0,8,17],[29,0,8,18],[30,0,8,25],[31,0,8,25],[32,0,8,25],[33,0,8,25],[34,0,8,25],[35,0,8,25],[36,0,8,25],[37,0,8,25],[38,0,8,25],[39,0,8,25]],[[12,0,8,8],[13,0,8,12],[14,0,8,12],[15,0,8,12],[16,0,8,12],[17,0,9,11],[18,0,9,19],[19,0,9,19],[20,0,9,19],[21,0,9,19],[22,0,9,19],[23,0,9,19],[24,0,9,19],[25,0,9,19],[26,0,9,20],[27,0,9,22],[28,0,9,22],[29,0,9,22],[30,0,9,22],[31,0,9,22]],[[0,0,8,8],[1,0,8,8],[2,0,8,8],[3,0,8,8],[4,0,8,8],[5,0,8,8],[6,0,8,8],[7,0,8,8],[8,0,8,8],[9,0,8,8],[10,0,8,8],[11,0,8,8],[12,0,8,8],[13,0,8,8],[14,0,8,8],[15,0,8,8],[16,0,8,12],[17,0,10,11],[18,0,10,11],[19,0,10,11],[20,0,10,11],[21,0,10,11],[22,0,10,11],[23,0,10,11],[24,0,10,11],[25,0,10,11],[26,0,10,11],[27,0,10,21],[28,0,10,22],[29,0,10,22],[30,0,10,22],[31,0,10,22],[32,0,10,22],[33,0,10,22],[34,0,10,22],[35,0,10,22],[36,0,10,22],[37,0,10,22],[38,0,10,32],[39,0,10,33],[40,0,10,37],[41,0,10,37],[42,0,10,37],[43,0,10,37],[44,0,10,37],[45,0,10,37],[46,0,10,37]],[[12,0,8,8],[13,0,8,12],[14,0,8,12],[15,0,8,12],[16,0,8,12],[17,0,11,11],[18,0,11,20],[19,0,11,20],[20,0,11,20],[21,0,11,20],[22,0,11,20],[23,0,11,20],[24,0,11,20],[25,0,11,20],[26,0,11,20],[27,0,11,21],[28,0,11,27],[29,0,11,27],[30,0,11,27],[31,0,11,27],[32,0,11,27],[33,0,11,27],[34,0,11,27],[35,0,11,27],[36,0,11,27]],[[0,0,8,8],[1,0,8,8],[2,0,8,8],[3,0,8,8],[4,0,8,8],[5,0,8,8],[6,0,8,8],[7,0,8,8],[8,0,8,8],[9,0,8,8],[10,0,8,8],[11,0,8,8],[12,0,8,8],[13,0,8,8],[14,0,8,8],[15,0,8,8],[16,0,8,12],[17,0,12,11],[18,0,12,11],[19,0,12,11],[20,0,12,11],[21,0,12,11],[22,0,12,11],[23,0,12,11],[24,0,12,18],[25,0,12,19],[26,0,12,19],[27,0,12,19],[28,0,12,22],[29,0,12,24],[30,0,12,24],[31,0,12,24],[32,0,12,24],[33,0,12,24]],[[0,0,13,12],[1,0,13,12],[2,0,13,12],[3,0,13,12],[4,0,13,12],[5,0,13,12],[6,0,13,12],[7,0,13,12],[8,0,13,12],[9,0,13,12],[10,0,13,12],[11,0,13,12],[12,0,13,12],[13,0,13,12],[14,0,13,12],[15,0,13,12],[16,0,13,12],[17,0,13,12],[18,0,13,12],[19,0,13,12],[20,0,13,16],[21,0,13,17],[22,0,13,17],[23,0,13,17],[24,0,13,17],[25,0,13,17],[26,0,13,17],[27,0,13,17],[28,0,13,24],[29,0,13,27],[30,0,13,27],[31,0,13,27],[32,0,13,27],[33,0,13,27],[34,0,13,27],[35,0,13,27],[36,0,13,27],[37,0,13,27],[38,0,13,27],[39,0,13,27],[40,0,13,27],[41,0,13,27],[42,0,13,27],[43,0,13,27],[44,0,13,27],[45,0,13,41],[46,0,13,41],[47,0,13,41]],[[12,0,14,10],[13,0,14,11],[14,0,14,11],[15,0,14,11],[16,0,14,11]],[],[[16,0,8,8],[17,0,8,12],[18,0,8,12],[19,0,8,12],[20,0,8,12],[21,0,8,12],[22,0,8,12],[23,0,8,12],[24,0,8,12],[25,0,8,12],[26,0,8,12],[27,0,8,12],[28,0,8,12]],[],[],[],[[8,0,8,8],[9,0,8,12],[10,0,8,12],[11,0,8,12],[12,0,8,12],[13,0,8,12],[14,0,8,12],[15,0,8,12],[16,0,8,12],[17,0,8,12],[18,0,8,12],[19,0,8,12],[20,0,8,12]],[],[],[[0,0,16,8],[1,0,16,8],[2,0,16,8],[3,0,16,8],[4,0,16,8],[5,0,16,8],[6,0,16,8],[7,0,16,8],[8,0,16,8],[9,0,16,8],[10,0,16,8],[11,0,16,8],[12,0,16,8],[13,0,16,8],[14,0,16,8],[15,0,16,8],[16,0,16,8],[17,0,16,13],[25,0,16,14],[26,0,16,141],[27,0,16,141],[28,0,16,141],[29,0,16,141],[30,0,16,141],[31,0,16,141],[32,0,16,141],[33,0,16,141],[34,0,16,141],[35,0,16,141],[36,0,16,141],[37,0,16,141],[38,0,16,141],[39,0,16,141],[40,0,16,141],[41,0,16,141],[42,0,16,141],[43,0,16,141],[44,0,16,141],[45,0,16,141],[46,0,16,141],[47,0,16,141],[48,0,16,141],[49,0,16,141],[50,0,16,141],[51,0,16,141],[52,0,16,141],[53,0,16,141],[54,0,16,141],[55,0,16,141],[56,0,16,141],[57,0,16,141],[58,0,16,141],[59,0,16,141],[60,0,16,141],[61,0,16,141],[62,0,16,141],[63,0,16,141],[64,0,16,141],[65,0,16,141],[66,0,16,141],[67,0,16,141],[68,0,16,141],[69,0,16,141],[70,0,16,141],[71,0,16,141],[72,0,16,141],[73,0,16,141],[74,0,16,141],[75,0,16,141],[76,0,16,141],[77,0,16,141],[78,0,16,141],[79,0,16,141],[80,0,16,141],[81,0,16,141],[82,0,16,141],[83,0,16,141],[84,0,16,141],[85,0,16,141],[86,0,16,141],[87,0,16,141],[88,0,16,141],[89,0,16,141],[90,0,16,141],[91,0,16,141],[92,0,16,141],[93,0,16,141],[94,0,16,141],[95,0,16,141],[96,0,16,141],[97,0,16,141],[98,0,16,141],[99,0,16,141],[100,0,16,141],[101,0,16,141],[102,0,16,141],[103,0,16,141],[104,0,16,141],[105,0,16,141],[106,0,16,141],[107,0,16,141],[108,0,16,141],[109,0,16,141],[110,0,16,141],[111,0,16,141],[112,0,16,141],[113,0,16,141],[114,0,16,141],[115,0,16,141],[116,0,16,141],[117,0,16,141],[118,0,16,141],[119,0,16,141],[120,0,16,141],[121,0,16,141],[122,0,16,141],[123,0,16,141],[124,0,16,141],[125,0,16,141],[126,0,16,141],[127,0,16,141],[128,0,16,141],[129,0,16,141],[130,0,16,141],[131,0,16,141],[132,0,16,141],[133,0,16,141],[134,0,16,141],[135,0,16,141],[136,0,16,141],[137,0,16,141],[138,0,16,141],[139,0,16,141],[140,0,16,141],[141,0,16,141],[142,0,16,141],[143,0,16,141],[144,0,16,141],[145,0,16,141],[146,0,16,141],[147,0,16,141],[148,0,16,141],[149,0,16,141],[150,0,16,141],[151,0,16,141],[152,0,16,141],[153,0,16,141],[154,0,16,141],[155,0,16,141]],[[12,0,16,8],[13,0,16,13],[14,0,16,13],[15,0,16,13],[16,0,16,13],[17,0,16,13],[18,0,17,11],[19,0,17,16],[20,0,17,16],[21,0,17,16],[22,0,17,16],[23,0,17,16],[24,0,17,17],[25,0,17,20],[26,0,17,20],[27,0,17,20],[28,0,17,20],[29,0,17,20],[30,0,17,20]],[],[[16,0,16,8],[17,0,16,13],[18,0,16,13],[19,0,16,13],[20,0,16,13],[21,0,16,13],[22,0,16,13],[23,0,16,13],[24,0,16,13],[25,0,16,13],[26,0,16,13],[27,0,16,13],[28,0,16,13],[29,0,16,13]],[],[],[],[[8,0,7,6],[9,0,7,12],[10,0,7,12],[11,0,7,12],[12,0,7,12],[13,0,7,12],[14,0,7,12],[15,0,7,12],[16,0,7,12],[17,0,7,12],[18,0,7,12],[19,0,7,12],[20,0,7,12],[21,0,7,12],[22,0,7,12]],[[8,0,6,4],[9,0,6,7],[10,0,6,7],[11,0,6,7],[12,0,6,7],[13,0,6,7],[14,0,6,7],[15,0,6,7],[16,0,6,7],[17,0,6,7],[18,0,6,7],[19,0,6,7]],[[0,0,22,3],[1,0,22,3],[2,0,22,3],[3,0,22,3],[4,0,22,3],[5,0,22,3],[6,0,22,3]],[],[],[],[],[],[],[],[]],"names":[],"sources":["/Users/ziyounian/DevEcoStudioProjects/MyApplication/entry/src/main/ets/pages/Index.ets"],"sourcesContent":["@Entry\n@Component\nstruct Index {\n  @State message: string = 'Hello World'\n\n  build() {\n    Row() {\n      Column() {\n        Text(this.message)\n          .fontSize(50)\n          .fontWeight(FontWeight.Bold)\n          .fontColor('#36D')\n          .onClick(() => {\n            this.message = 'Hello ArkTS!'\n          })\n\n        Image('https://res.vmallres.com/pimages//uomcdn/CN/pms/202305/gbom/6942103102790/group//428_428_B5CF48BC9E98F629F44ED8DF4F70EB86.png')\n          .width(250)\n      }\n      .width('100%')\n    }\n    .height('100%')\n  }\n}"]},"resolvedIds":{},"sourcemapChain":[],"syntheticNamedExports":false,"transformDependencies":[],"cacheAst":{"dynamicImportCache":[],"exportAllDeclarationCache":[],"exportNamedDeclarationCache":[],"importCache":[]}},{"assertions":{},"code":"import UIAbility from '@ohos.app.ability.UIAbility';\r\nimport hilog from '@ohos.hilog';\r\nexport default class EntryAbility extends UIAbility {\r\n    onCreate(want, launchParam) {\r\n        hilog.info(0x0000, 'testTag', '%{public}s', 'Ability onCreate');\r\n    }\r\n    onDestroy() {\r\n        hilog.info(0x0000, 'testTag', '%{public}s', 'Ability onDestroy');\r\n    }\r\n    onWindowStageCreate(windowStage) {\r\n        // Main window is created, set main page for this ability\r\n        hilog.info(0x0000, 'testTag', '%{public}s', 'Ability onWindowStageCreate');\r\n        windowStage.loadContent('pages/Index', (err, data) => {\r\n            var _a, _b;\r\n            if (err.code) {\r\n                hilog.error(0x0000, 'testTag', 'Failed to load the content. Cause: %{public}s', (_a = JSON.stringify(err)) !== null && _a !== void 0 ? _a : '');\r\n                return;\r\n            }\r\n            hilog.info(0x0000, 'testTag', 'Succeeded in loading the content. Data: %{public}s', (_b = JSON.stringify(data)) !== null && _b !== void 0 ? _b : '');\r\n        });\r\n    }\r\n    onWindowStageDestroy() {\r\n        // Main window is destroyed, release UI related resources\r\n        hilog.info(0x0000, 'testTag', '%{public}s', 'Ability onWindowStageDestroy');\r\n    }\r\n    onForeground() {\r\n        // Ability has brought to foreground\r\n        hilog.info(0x0000, 'testTag', '%{public}s', 'Ability onForeground');\r\n    }\r\n    onBackground() {\r\n        // Ability has back to background\r\n        hilog.info(0x0000, 'testTag', '%{public}s', 'Ability onBackground');\r\n    }\r\n}\r\n//# sourceMappingURL=EntryAbility.js.map","customTransformCache":false,"dependencies":["\u0000rollup_plugin_ignore_empty_module_placeholder"],"id":"/Users/ziyounian/DevEcoStudioProjects/MyApplication/entry/src/main/ets/entryability/EntryAbility.ts","meta":{"hostModulesInfo":[],"moduleName":"entry","isLocalDependency":true,"isNodeEntryFile":false,"pkgPath":"/Users/ziyounian/DevEcoStudioProjects/MyApplication/entry"},"moduleSideEffects":true,"originalCode":"import UIAbility from '@ohos.app.ability.UIAbility';\nimport hilog from '@ohos.hilog';\nimport window from '@ohos.window';\n\nexport default class EntryAbility extends UIAbility {\n  onCreate(want, launchParam) {\n    hilog.info(0x0000, 'testTag', '%{public}s', 'Ability onCreate');\n  }\n\n  onDestroy() {\n    hilog.info(0x0000, 'testTag', '%{public}s', 'Ability onDestroy');\n  }\n\n  onWindowStageCreate(windowStage: window.WindowStage) {\n    // Main window is created, set main page for this ability\n    hilog.info(0x0000, 'testTag', '%{public}s', 'Ability onWindowStageCreate');\n\n    windowStage.loadContent('pages/Index', (err, data) => {\n      if (err.code) {\n        hilog.error(0x0000, 'testTag', 'Failed to load the content. Cause: %{public}s', JSON.stringify(err) ?? '');\n        return;\n      }\n      hilog.info(0x0000, 'testTag', 'Succeeded in loading the content. Data: %{public}s', JSON.stringify(data) ?? '');\n    });\n  }\n\n  onWindowStageDestroy() {\n    // Main window is destroyed, release UI related resources\n    hilog.info(0x0000, 'testTag', '%{public}s', 'Ability onWindowStageDestroy');\n  }\n\n  onForeground() {\n    // Ability has brought to foreground\n    hilog.info(0x0000, 'testTag', '%{public}s', 'Ability onForeground');\n  }\n\n  onBackground() {\n    // Ability has back to background\n    hilog.info(0x0000, 'testTag', '%{public}s', 'Ability onBackground');\n  }\n}\n","originalSourcemap":{"version":3,"mappings":[[[0,0,0,0],[1,0,0,7],[2,0,0,7],[3,0,0,7],[4,0,0,7],[5,0,0,7],[6,0,0,7],[7,0,0,7],[8,0,0,7],[9,0,0,7],[10,0,0,7],[11,0,0,7],[12,0,0,7],[13,0,0,7],[14,0,0,7],[15,0,0,7],[16,0,0,16],[17,0,0,22],[18,0,0,22],[19,0,0,22],[20,0,0,22],[21,0,0,22],[22,0,0,22],[23,0,0,22],[24,0,0,22],[25,0,0,22],[26,0,0,22],[27,0,0,22],[28,0,0,22],[29,0,0,22],[30,0,0,22],[31,0,0,22],[32,0,0,22],[33,0,0,22],[34,0,0,22],[35,0,0,22],[36,0,0,22],[37,0,0,22],[38,0,0,22],[39,0,0,22],[40,0,0,22],[41,0,0,22],[42,0,0,22],[43,0,0,22],[44,0,0,22],[45,0,0,22],[46,0,0,22],[47,0,0,22],[48,0,0,22],[49,0,0,22],[50,0,0,22],[51,0,0,51],[52,0,0,52],[53,0,0,52]],[[0,0,1,0],[1,0,1,7],[2,0,1,7],[3,0,1,7],[4,0,1,7],[5,0,1,7],[6,0,1,7],[7,0,1,7],[8,0,1,7],[9,0,1,7],[10,0,1,7],[11,0,1,7],[12,0,1,12],[13,0,1,18],[14,0,1,18],[15,0,1,18],[16,0,1,18],[17,0,1,18],[18,0,1,18],[19,0,1,18],[20,0,1,18],[21,0,1,18],[22,0,1,18],[23,0,1,18],[24,0,1,18],[25,0,1,18],[26,0,1,18],[27,0,1,18],[28,0,1,18],[29,0,1,18],[30,0,1,18],[31,0,1,31],[32,0,1,32],[33,0,1,32]],[[0,0,4,0],[1,0,4,0],[2,0,4,0],[3,0,4,0],[4,0,4,0],[5,0,4,0],[6,0,4,6],[7,0,4,7],[8,0,4,7],[9,0,4,7],[10,0,4,7],[11,0,4,7],[12,0,4,7],[13,0,4,7],[14,0,4,14],[15,0,4,21],[16,0,4,21],[17,0,4,21],[18,0,4,21],[19,0,4,21],[20,0,4,21],[21,0,4,21],[22,0,4,21],[23,0,4,21],[24,0,4,21],[25,0,4,21],[26,0,4,21],[27,0,4,21],[28,0,4,21],[29,0,4,21],[30,0,4,21],[31,0,4,21],[32,0,4,21],[33,0,4,34],[42,0,4,42],[43,0,4,51],[44,0,4,51],[45,0,4,51],[46,0,4,51],[47,0,4,51],[48,0,4,51],[49,0,4,51],[50,0,4,51],[51,0,4,51],[52,0,4,51],[53,0,4,51],[54,0,4,51]],[[4,0,5,2],[5,0,5,10],[6,0,5,10],[7,0,5,10],[8,0,5,10],[9,0,5,10],[10,0,5,10],[11,0,5,10],[12,0,5,10],[13,0,5,11],[14,0,5,15],[15,0,5,15],[16,0,5,15],[17,0,5,15],[18,0,5,15],[19,0,5,17],[20,0,5,28],[21,0,5,28],[22,0,5,28],[23,0,5,28],[24,0,5,28],[25,0,5,28],[26,0,5,28],[27,0,5,28],[28,0,5,28],[29,0,5,28],[30,0,5,28],[31,0,5,28],[32,0,5,28],[33,0,5,28],[34,0,5,28]],[[8,0,6,4],[9,0,6,9],[10,0,6,9],[11,0,6,9],[12,0,6,9],[13,0,6,9],[14,0,6,10],[15,0,6,14],[16,0,6,14],[17,0,6,14],[18,0,6,14],[19,0,6,15],[20,0,6,21],[21,0,6,21],[22,0,6,21],[23,0,6,21],[24,0,6,21],[25,0,6,21],[26,0,6,21],[27,0,6,23],[28,0,6,32],[29,0,6,32],[30,0,6,32],[31,0,6,32],[32,0,6,32],[33,0,6,32],[34,0,6,32],[35,0,6,32],[36,0,6,32],[37,0,6,32],[38,0,6,34],[39,0,6,46],[40,0,6,46],[41,0,6,46],[42,0,6,46],[43,0,6,46],[44,0,6,46],[45,0,6,46],[46,0,6,46],[47,0,6,46],[48,0,6,46],[49,0,6,46],[50,0,6,46],[51,0,6,46],[52,0,6,48],[53,0,6,66],[54,0,6,66],[55,0,6,66],[56,0,6,66],[57,0,6,66],[58,0,6,66],[59,0,6,66],[60,0,6,66],[61,0,6,66],[62,0,6,66],[63,0,6,66],[64,0,6,66],[65,0,6,66],[66,0,6,66],[67,0,6,66],[68,0,6,66],[69,0,6,66],[70,0,6,66],[71,0,6,67],[72,0,6,68],[73,0,6,68]],[[4,0,7,2],[5,0,7,3],[6,0,7,3]],[[4,0,9,2],[5,0,9,11],[6,0,9,11],[7,0,9,11],[8,0,9,11],[9,0,9,11],[10,0,9,11],[11,0,9,11],[12,0,9,11],[13,0,9,11],[14,0,9,11],[15,0,9,11],[16,0,9,11],[17,0,9,11],[18,0,9,11]],[[8,0,10,4],[9,0,10,9],[10,0,10,9],[11,0,10,9],[12,0,10,9],[13,0,10,9],[14,0,10,10],[15,0,10,14],[16,0,10,14],[17,0,10,14],[18,0,10,14],[19,0,10,15],[20,0,10,21],[21,0,10,21],[22,0,10,21],[23,0,10,21],[24,0,10,21],[25,0,10,21],[26,0,10,21],[27,0,10,23],[28,0,10,32],[29,0,10,32],[30,0,10,32],[31,0,10,32],[32,0,10,32],[33,0,10,32],[34,0,10,32],[35,0,10,32],[36,0,10,32],[37,0,10,32],[38,0,10,34],[39,0,10,46],[40,0,10,46],[41,0,10,46],[42,0,10,46],[43,0,10,46],[44,0,10,46],[45,0,10,46],[46,0,10,46],[47,0,10,46],[48,0,10,46],[49,0,10,46],[50,0,10,46],[51,0,10,46],[52,0,10,48],[53,0,10,67],[54,0,10,67],[55,0,10,67],[56,0,10,67],[57,0,10,67],[58,0,10,67],[59,0,10,67],[60,0,10,67],[61,0,10,67],[62,0,10,67],[63,0,10,67],[64,0,10,67],[65,0,10,67],[66,0,10,67],[67,0,10,67],[68,0,10,67],[69,0,10,67],[70,0,10,67],[71,0,10,67],[72,0,10,68],[73,0,10,69],[74,0,10,69]],[[4,0,11,2],[5,0,11,3],[6,0,11,3]],[[0,0,13,2],[1,0,13,2],[2,0,13,2],[3,0,13,2],[4,0,13,2],[5,0,13,2],[6,0,13,2],[7,0,13,2],[8,0,13,2],[9,0,13,2],[10,0,13,2],[11,0,13,2],[12,0,13,2],[13,0,13,2],[14,0,13,2],[15,0,13,2],[16,0,13,2],[17,0,13,2],[18,0,13,2],[19,0,13,2],[20,0,13,2],[21,0,13,2],[22,0,13,2],[23,0,13,21],[24,0,13,22],[25,0,13,53],[26,0,13,53],[27,0,13,53],[28,0,13,53],[29,0,13,53],[30,0,13,53],[31,0,13,53],[32,0,13,53],[33,0,13,53],[34,0,13,53],[35,0,13,53],[36,0,13,53],[37,0,13,53],[38,0,13,53],[39,0,13,53]],[[8,0,14,4],[9,0,14,61],[10,0,14,61],[11,0,14,61],[12,0,14,61],[13,0,14,61],[14,0,14,61],[15,0,14,61],[16,0,14,61],[17,0,14,61],[18,0,14,61],[19,0,14,61],[20,0,14,61],[21,0,14,61],[22,0,14,61],[23,0,14,61],[24,0,14,61],[25,0,14,61],[26,0,14,61],[27,0,14,61],[28,0,14,61],[29,0,14,61],[30,0,14,61],[31,0,14,61],[32,0,14,61],[33,0,14,61],[34,0,14,61],[35,0,14,61],[36,0,14,61],[37,0,14,61],[38,0,14,61],[39,0,14,61],[40,0,14,61],[41,0,14,61],[42,0,14,61],[43,0,14,61],[44,0,14,61],[45,0,14,61],[46,0,14,61],[47,0,14,61],[48,0,14,61],[49,0,14,61],[50,0,14,61],[51,0,14,61],[52,0,14,61],[53,0,14,61],[54,0,14,61],[55,0,14,61],[56,0,14,61],[57,0,14,61],[58,0,14,61],[59,0,14,61],[60,0,14,61],[61,0,14,61],[62,0,14,61],[63,0,14,61],[64,0,14,61],[65,0,14,61],[66,0,14,61]],[[8,0,15,4],[9,0,15,9],[10,0,15,9],[11,0,15,9],[12,0,15,9],[13,0,15,9],[14,0,15,10],[15,0,15,14],[16,0,15,14],[17,0,15,14],[18,0,15,14],[19,0,15,15],[20,0,15,21],[21,0,15,21],[22,0,15,21],[23,0,15,21],[24,0,15,21],[25,0,15,21],[26,0,15,21],[27,0,15,23],[28,0,15,32],[29,0,15,32],[30,0,15,32],[31,0,15,32],[32,0,15,32],[33,0,15,32],[34,0,15,32],[35,0,15,32],[36,0,15,32],[37,0,15,32],[38,0,15,34],[39,0,15,46],[40,0,15,46],[41,0,15,46],[42,0,15,46],[43,0,15,46],[44,0,15,46],[45,0,15,46],[46,0,15,46],[47,0,15,46],[48,0,15,46],[49,0,15,46],[50,0,15,46],[51,0,15,46],[52,0,15,48],[53,0,15,77],[54,0,15,77],[55,0,15,77],[56,0,15,77],[57,0,15,77],[58,0,15,77],[59,0,15,77],[60,0,15,77],[61,0,15,77],[62,0,15,77],[63,0,15,77],[64,0,15,77],[65,0,15,77],[66,0,15,77],[67,0,15,77],[68,0,15,77],[69,0,15,77],[70,0,15,77],[71,0,15,77],[72,0,15,77],[73,0,15,77],[74,0,15,77],[75,0,15,77],[76,0,15,77],[77,0,15,77],[78,0,15,77],[79,0,15,77],[80,0,15,77],[81,0,15,77],[82,0,15,78],[83,0,15,79],[84,0,15,79]],[[8,0,17,4],[9,0,17,15],[10,0,17,15],[11,0,17,15],[12,0,17,15],[13,0,17,15],[14,0,17,15],[15,0,17,15],[16,0,17,15],[17,0,17,15],[18,0,17,15],[19,0,17,15],[20,0,17,16],[21,0,17,27],[22,0,17,27],[23,0,17,27],[24,0,17,27],[25,0,17,27],[26,0,17,27],[27,0,17,27],[28,0,17,27],[29,0,17,27],[30,0,17,27],[31,0,17,27],[32,0,17,28],[33,0,17,41],[34,0,17,41],[35,0,17,41],[36,0,17,41],[37,0,17,41],[38,0,17,41],[39,0,17,41],[40,0,17,41],[41,0,17,41],[42,0,17,41],[43,0,17,41],[44,0,17,41],[45,0,17,41],[46,0,17,41],[47,0,17,43],[48,0,17,44],[49,0,17,47],[50,0,17,47],[51,0,17,47],[52,0,17,47],[53,0,17,49],[54,0,17,53],[55,0,17,53],[56,0,17,53],[57,0,17,53],[58,0,17,53],[59,0,17,55],[60,0,17,57],[61,0,17,57],[62,0,17,57],[63,0,17,57],[64,0,17,57]],[],[[12,0,18,6],[13,0,18,10],[14,0,18,10],[15,0,18,10],[16,0,18,10],[17,0,18,10],[18,0,18,10],[19,0,18,13],[20,0,18,14],[21,0,18,14],[22,0,18,14],[23,0,18,14],[24,0,18,18],[25,0,18,20],[26,0,18,20],[27,0,18,20],[28,0,18,20]],[[0,0,19,8],[1,0,19,8],[2,0,19,8],[3,0,19,8],[4,0,19,8],[5,0,19,8],[6,0,19,8],[7,0,19,8],[8,0,19,8],[9,0,19,8],[10,0,19,8],[11,0,19,8],[12,0,19,8],[13,0,19,8],[14,0,19,8],[15,0,19,8],[16,0,19,8],[17,0,19,8],[18,0,19,8],[19,0,19,8],[20,0,19,8],[21,0,19,13],[22,0,19,14],[23,0,19,19],[24,0,19,19],[25,0,19,19],[26,0,19,19],[27,0,19,19],[28,0,19,20],[34,0,19,26],[35,0,19,28],[36,0,19,28],[37,0,19,28],[38,0,19,28],[39,0,19,28],[40,0,19,28],[41,0,19,28],[42,0,19,28],[43,0,19,28],[44,0,19,28],[45,0,19,37],[47,0,19,39],[48,0,19,86],[49,0,19,86],[50,0,19,86],[51,0,19,86],[52,0,19,86],[53,0,19,86],[54,0,19,86],[55,0,19,86],[56,0,19,86],[57,0,19,86],[58,0,19,86],[59,0,19,86],[60,0,19,86],[61,0,19,86],[62,0,19,86],[63,0,19,86],[64,0,19,86],[65,0,19,86],[66,0,19,86],[67,0,19,86],[68,0,19,86],[69,0,19,86],[70,0,19,86],[71,0,19,86],[72,0,19,86],[73,0,19,86],[74,0,19,86],[75,0,19,86],[76,0,19,86],[77,0,19,86],[78,0,19,86],[79,0,19,86],[80,0,19,86],[81,0,19,86],[82,0,19,86],[83,0,19,86],[84,0,19,86],[85,0,19,86],[86,0,19,86],[87,0,19,86],[88,0,19,86],[89,0,19,86],[90,0,19,86],[91,0,19,86],[92,0,19,86],[93,0,19,86],[94,0,19,86],[95,0,19,86],[96,0,19,88],[102,0,19,88],[103,0,19,92],[104,0,19,92],[105,0,19,92],[106,0,19,92],[107,0,19,93],[116,0,19,102],[117,0,19,103],[118,0,19,103],[119,0,19,103],[120,0,19,106],[121,0,19,107],[122,0,19,111],[123,0,19,111],[124,0,19,111],[125,0,19,111],[126,0,19,111],[127,0,19,111],[128,0,19,111],[129,0,19,111],[130,0,19,111],[131,0,19,111],[132,0,19,111],[133,0,19,111],[134,0,19,111],[135,0,19,111],[136,0,19,111],[137,0,19,111],[138,0,19,111],[139,0,19,111],[140,0,19,111],[141,0,19,111],[142,0,19,111],[143,0,19,111],[144,0,19,111],[145,0,19,111],[146,0,19,111],[147,0,19,111],[148,0,19,111],[149,0,19,111],[150,0,19,111],[151,0,19,111],[152,0,19,111],[153,0,19,111],[154,0,19,111],[155,0,19,111],[156,0,19,111],[157,0,19,111],[158,0,19,113],[159,0,19,114],[160,0,19,115],[161,0,19,115]],[[16,0,20,8],[17,0,20,15],[18,0,20,15],[19,0,20,15],[20,0,20,15],[21,0,20,15],[22,0,20,15],[23,0,20,15],[24,0,20,15]],[[0,0,21,7],[1,0,21,7],[2,0,21,7],[3,0,21,7],[4,0,21,7],[5,0,21,7],[6,0,21,7],[7,0,21,7],[8,0,21,7],[9,0,21,7],[10,0,21,7],[11,0,21,7],[12,0,21,7],[13,0,21,7],[14,0,21,7]],[[0,0,22,6],[1,0,22,6],[2,0,22,6],[3,0,22,6],[4,0,22,6],[5,0,22,6],[6,0,22,6],[7,0,22,6],[8,0,22,6],[9,0,22,6],[10,0,22,6],[11,0,22,6],[12,0,22,6],[13,0,22,6],[14,0,22,6],[15,0,22,6],[16,0,22,6],[17,0,22,11],[18,0,22,12],[19,0,22,16],[20,0,22,16],[21,0,22,16],[22,0,22,16],[23,0,22,17],[29,0,22,23],[30,0,22,25],[31,0,22,25],[32,0,22,25],[33,0,22,25],[34,0,22,25],[35,0,22,25],[36,0,22,25],[37,0,22,25],[38,0,22,25],[39,0,22,25],[40,0,22,34],[42,0,22,36],[43,0,22,88],[44,0,22,88],[45,0,22,88],[46,0,22,88],[47,0,22,88],[48,0,22,88],[49,0,22,88],[50,0,22,88],[51,0,22,88],[52,0,22,88],[53,0,22,88],[54,0,22,88],[55,0,22,88],[56,0,22,88],[57,0,22,88],[58,0,22,88],[59,0,22,88],[60,0,22,88],[61,0,22,88],[62,0,22,88],[63,0,22,88],[64,0,22,88],[65,0,22,88],[66,0,22,88],[67,0,22,88],[68,0,22,88],[69,0,22,88],[70,0,22,88],[71,0,22,88],[72,0,22,88],[73,0,22,88],[74,0,22,88],[75,0,22,88],[76,0,22,88],[77,0,22,88],[78,0,22,88],[79,0,22,88],[80,0,22,88],[81,0,22,88],[82,0,22,88],[83,0,22,88],[84,0,22,88],[85,0,22,88],[86,0,22,88],[87,0,22,88],[88,0,22,88],[89,0,22,88],[90,0,22,88],[91,0,22,88],[92,0,22,88],[93,0,22,88],[94,0,22,88],[95,0,22,88],[96,0,22,90],[102,0,22,90],[103,0,22,94],[104,0,22,94],[105,0,22,94],[106,0,22,94],[107,0,22,95],[116,0,22,104],[117,0,22,105],[118,0,22,105],[119,0,22,105],[120,0,22,105],[121,0,22,109],[122,0,22,110],[123,0,22,114],[124,0,22,114],[125,0,22,114],[126,0,22,114],[127,0,22,114],[128,0,22,114],[129,0,22,114],[130,0,22,114],[131,0,22,114],[132,0,22,114],[133,0,22,114],[134,0,22,114],[135,0,22,114],[136,0,22,114],[137,0,22,114],[138,0,22,114],[139,0,22,114],[140,0,22,114],[141,0,22,114],[142,0,22,114],[143,0,22,114],[144,0,22,114],[145,0,22,114],[146,0,22,114],[147,0,22,114],[148,0,22,114],[149,0,22,114],[150,0,22,114],[151,0,22,114],[152,0,22,114],[153,0,22,114],[154,0,22,114],[155,0,22,114],[156,0,22,114],[157,0,22,114],[158,0,22,114],[159,0,22,116],[160,0,22,117],[161,0,22,118],[162,0,22,118]],[[0,0,23,4],[1,0,23,4],[2,0,23,4],[3,0,23,4],[4,0,23,4],[5,0,23,4],[6,0,23,4],[7,0,23,4],[8,0,23,4],[9,0,23,5],[10,0,23,6],[11,0,23,7],[12,0,23,7]],[[4,0,24,2],[5,0,24,3],[6,0,24,3]],[[4,0,26,2],[5,0,26,22],[6,0,26,22],[7,0,26,22],[8,0,26,22],[9,0,26,22],[10,0,26,22],[11,0,26,22],[12,0,26,22],[13,0,26,22],[14,0,26,22],[15,0,26,22],[16,0,26,22],[17,0,26,22],[18,0,26,22],[19,0,26,22],[20,0,26,22],[21,0,26,22],[22,0,26,22],[23,0,26,22],[24,0,26,22],[25,0,26,22],[26,0,26,22],[27,0,26,22],[28,0,26,22],[29,0,26,22]],[[8,0,27,4],[9,0,27,61],[10,0,27,61],[11,0,27,61],[12,0,27,61],[13,0,27,61],[14,0,27,61],[15,0,27,61],[16,0,27,61],[17,0,27,61],[18,0,27,61],[19,0,27,61],[20,0,27,61],[21,0,27,61],[22,0,27,61],[23,0,27,61],[24,0,27,61],[25,0,27,61],[26,0,27,61],[27,0,27,61],[28,0,27,61],[29,0,27,61],[30,0,27,61],[31,0,27,61],[32,0,27,61],[33,0,27,61],[34,0,27,61],[35,0,27,61],[36,0,27,61],[37,0,27,61],[38,0,27,61],[39,0,27,61],[40,0,27,61],[41,0,27,61],[42,0,27,61],[43,0,27,61],[44,0,27,61],[45,0,27,61],[46,0,27,61],[47,0,27,61],[48,0,27,61],[49,0,27,61],[50,0,27,61],[51,0,27,61],[52,0,27,61],[53,0,27,61],[54,0,27,61],[55,0,27,61],[56,0,27,61],[57,0,27,61],[58,0,27,61],[59,0,27,61],[60,0,27,61],[61,0,27,61],[62,0,27,61],[63,0,27,61],[64,0,27,61],[65,0,27,61],[66,0,27,61]],[[8,0,28,4],[9,0,28,9],[10,0,28,9],[11,0,28,9],[12,0,28,9],[13,0,28,9],[14,0,28,10],[15,0,28,14],[16,0,28,14],[17,0,28,14],[18,0,28,14],[19,0,28,15],[20,0,28,21],[21,0,28,21],[22,0,28,21],[23,0,28,21],[24,0,28,21],[25,0,28,21],[26,0,28,21],[27,0,28,23],[28,0,28,32],[29,0,28,32],[30,0,28,32],[31,0,28,32],[32,0,28,32],[33,0,28,32],[34,0,28,32],[35,0,28,32],[36,0,28,32],[37,0,28,32],[38,0,28,34],[39,0,28,46],[40,0,28,46],[41,0,28,46],[42,0,28,46],[43,0,28,46],[44,0,28,46],[45,0,28,46],[46,0,28,46],[47,0,28,46],[48,0,28,46],[49,0,28,46],[50,0,28,46],[51,0,28,46],[52,0,28,48],[53,0,28,78],[54,0,28,78],[55,0,28,78],[56,0,28,78],[57,0,28,78],[58,0,28,78],[59,0,28,78],[60,0,28,78],[61,0,28,78],[62,0,28,78],[63,0,28,78],[64,0,28,78],[65,0,28,78],[66,0,28,78],[67,0,28,78],[68,0,28,78],[69,0,28,78],[70,0,28,78],[71,0,28,78],[72,0,28,78],[73,0,28,78],[74,0,28,78],[75,0,28,78],[76,0,28,78],[77,0,28,78],[78,0,28,78],[79,0,28,78],[80,0,28,78],[81,0,28,78],[82,0,28,78],[83,0,28,79],[84,0,28,80],[85,0,28,80]],[[4,0,29,2],[5,0,29,3],[6,0,29,3]],[[4,0,31,2],[5,0,31,14],[6,0,31,14],[7,0,31,14],[8,0,31,14],[9,0,31,14],[10,0,31,14],[11,0,31,14],[12,0,31,14],[13,0,31,14],[14,0,31,14],[15,0,31,14],[16,0,31,14],[17,0,31,14],[18,0,31,14],[19,0,31,14],[20,0,31,14],[21,0,31,14]],[[8,0,32,4],[9,0,32,40],[10,0,32,40],[11,0,32,40],[12,0,32,40],[13,0,32,40],[14,0,32,40],[15,0,32,40],[16,0,32,40],[17,0,32,40],[18,0,32,40],[19,0,32,40],[20,0,32,40],[21,0,32,40],[22,0,32,40],[23,0,32,40],[24,0,32,40],[25,0,32,40],[26,0,32,40],[27,0,32,40],[28,0,32,40],[29,0,32,40],[30,0,32,40],[31,0,32,40],[32,0,32,40],[33,0,32,40],[34,0,32,40],[35,0,32,40],[36,0,32,40],[37,0,32,40],[38,0,32,40],[39,0,32,40],[40,0,32,40],[41,0,32,40],[42,0,32,40],[43,0,32,40],[44,0,32,40],[45,0,32,40]],[[8,0,33,4],[9,0,33,9],[10,0,33,9],[11,0,33,9],[12,0,33,9],[13,0,33,9],[14,0,33,10],[15,0,33,14],[16,0,33,14],[17,0,33,14],[18,0,33,14],[19,0,33,15],[20,0,33,21],[21,0,33,21],[22,0,33,21],[23,0,33,21],[24,0,33,21],[25,0,33,21],[26,0,33,21],[27,0,33,23],[28,0,33,32],[29,0,33,32],[30,0,33,32],[31,0,33,32],[32,0,33,32],[33,0,33,32],[34,0,33,32],[35,0,33,32],[36,0,33,32],[37,0,33,32],[38,0,33,34],[39,0,33,46],[40,0,33,46],[41,0,33,46],[42,0,33,46],[43,0,33,46],[44,0,33,46],[45,0,33,46],[46,0,33,46],[47,0,33,46],[48,0,33,46],[49,0,33,46],[50,0,33,46],[51,0,33,46],[52,0,33,48],[53,0,33,70],[54,0,33,70],[55,0,33,70],[56,0,33,70],[57,0,33,70],[58,0,33,70],[59,0,33,70],[60,0,33,70],[61,0,33,70],[62,0,33,70],[63,0,33,70],[64,0,33,70],[65,0,33,70],[66,0,33,70],[67,0,33,70],[68,0,33,70],[69,0,33,70],[70,0,33,70],[71,0,33,70],[72,0,33,70],[73,0,33,70],[74,0,33,70],[75,0,33,71],[76,0,33,72],[77,0,33,72]],[[4,0,34,2],[5,0,34,3],[6,0,34,3]],[[4,0,36,2],[5,0,36,14],[6,0,36,14],[7,0,36,14],[8,0,36,14],[9,0,36,14],[10,0,36,14],[11,0,36,14],[12,0,36,14],[13,0,36,14],[14,0,36,14],[15,0,36,14],[16,0,36,14],[17,0,36,14],[18,0,36,14],[19,0,36,14],[20,0,36,14],[21,0,36,14]],[[8,0,37,4],[9,0,37,37],[10,0,37,37],[11,0,37,37],[12,0,37,37],[13,0,37,37],[14,0,37,37],[15,0,37,37],[16,0,37,37],[17,0,37,37],[18,0,37,37],[19,0,37,37],[20,0,37,37],[21,0,37,37],[22,0,37,37],[23,0,37,37],[24,0,37,37],[25,0,37,37],[26,0,37,37],[27,0,37,37],[28,0,37,37],[29,0,37,37],[30,0,37,37],[31,0,37,37],[32,0,37,37],[33,0,37,37],[34,0,37,37],[35,0,37,37],[36,0,37,37],[37,0,37,37],[38,0,37,37],[39,0,37,37],[40,0,37,37],[41,0,37,37],[42,0,37,37]],[[8,0,38,4],[9,0,38,9],[10,0,38,9],[11,0,38,9],[12,0,38,9],[13,0,38,9],[14,0,38,10],[15,0,38,14],[16,0,38,14],[17,0,38,14],[18,0,38,14],[19,0,38,15],[20,0,38,21],[21,0,38,21],[22,0,38,21],[23,0,38,21],[24,0,38,21],[25,0,38,21],[26,0,38,21],[27,0,38,23],[28,0,38,32],[29,0,38,32],[30,0,38,32],[31,0,38,32],[32,0,38,32],[33,0,38,32],[34,0,38,32],[35,0,38,32],[36,0,38,32],[37,0,38,32],[38,0,38,34],[39,0,38,46],[40,0,38,46],[41,0,38,46],[42,0,38,46],[43,0,38,46],[44,0,38,46],[45,0,38,46],[46,0,38,46],[47,0,38,46],[48,0,38,46],[49,0,38,46],[50,0,38,46],[51,0,38,46],[52,0,38,48],[53,0,38,70],[54,0,38,70],[55,0,38,70],[56,0,38,70],[57,0,38,70],[58,0,38,70],[59,0,38,70],[60,0,38,70],[61,0,38,70],[62,0,38,70],[63,0,38,70],[64,0,38,70],[65,0,38,70],[66,0,38,70],[67,0,38,70],[68,0,38,70],[69,0,38,70],[70,0,38,70],[71,0,38,70],[72,0,38,70],[73,0,38,70],[74,0,38,70],[75,0,38,71],[76,0,38,72],[77,0,38,72]],[[4,0,39,2],[5,0,39,3],[6,0,39,3]],[[0,0,40,1],[1,0,40,1],[2,0,40,1]],[]],"names":[],"sources":["/Users/ziyounian/DevEcoStudioProjects/MyApplication/entry/src/main/ets/entryability/EntryAbility.ts"],"sourcesContent":["import UIAbility from '@ohos.app.ability.UIAbility';\nimport hilog from '@ohos.hilog';\nimport window from '@ohos.window';\n\nexport default class EntryAbility extends UIAbility {\n  onCreate(want, launchParam) {\n    hilog.info(0x0000, 'testTag', '%{public}s', 'Ability onCreate');\n  }\n\n  onDestroy() {\n    hilog.info(0x0000, 'testTag', '%{public}s', 'Ability onDestroy');\n  }\n\n  onWindowStageCreate(windowStage: window.WindowStage) {\n    // Main window is created, set main page for this ability\n    hilog.info(0x0000, 'testTag', '%{public}s', 'Ability onWindowStageCreate');\n\n    windowStage.loadContent('pages/Index', (err, data) => {\n      if (err.code) {\n        hilog.error(0x0000, 'testTag', 'Failed to load the content. Cause: %{public}s', JSON.stringify(err) ?? '');\n        return;\n      }\n      hilog.info(0x0000, 'testTag', 'Succeeded in loading the content. Data: %{public}s', JSON.stringify(data) ?? '');\n    });\n  }\n\n  onWindowStageDestroy() {\n    // Main window is destroyed, release UI related resources\n    hilog.info(0x0000, 'testTag', '%{public}s', 'Ability onWindowStageDestroy');\n  }\n\n  onForeground() {\n    // Ability has brought to foreground\n    hilog.info(0x0000, 'testTag', '%{public}s', 'Ability onForeground');\n  }\n\n  onBackground() {\n    // Ability has back to background\n    hilog.info(0x0000, 'testTag', '%{public}s', 'Ability onBackground');\n  }\n}\n"]},"resolvedIds":{"@ohos.app.ability.UIAbility":{"assertions":{},"external":false,"id":"\u0000rollup_plugin_ignore_empty_module_placeholder","meta":{},"moduleSideEffects":true,"resolvedBy":"ignorePlugin","syntheticNamedExports":false},"@ohos.hilog":{"assertions":{},"external":false,"id":"\u0000rollup_plugin_ignore_empty_module_placeholder","meta":{},"moduleSideEffects":true,"resolvedBy":"ignorePlugin","syntheticNamedExports":false}},"sourcemapChain":[],"syntheticNamedExports":false,"transformDependencies":[],"cacheAst":{"dynamicImportCache":[],"exportAllDeclarationCache":[],"exportNamedDeclarationCache":[],"importCache":[{"type":"ImportDeclaration","start":0,"end":52,"specifiers":[{"type":"ImportDefaultSpecifier","start":7,"end":16,"local":{"type":"Identifier","start":7,"end":16,"name":"UIAbility"}}],"source":{"type":"Literal","start":22,"end":51,"value":"@ohos.app.ability.UIAbility","raw":"'@ohos.app.ability.UIAbility'"}},{"type":"ImportDeclaration","start":54,"end":86,"specifiers":[{"type":"ImportDefaultSpecifier","start":61,"end":66,"local":{"type":"Identifier","start":61,"end":66,"name":"hilog"}}],"source":{"type":"Literal","start":72,"end":85,"value":"@ohos.hilog","raw":"'@ohos.hilog'"}}]}},{"assertions":{},"code":"export default {}","customTransformCache":false,"dependencies":[],"id":"\u0000rollup_plugin_ignore_empty_module_placeholder","meta":{"hostModulesInfo":[{"hostDependencyName":"@ohos.app.ability.UIAbility","hostModuleName":"entry"},{"hostDependencyName":"@ohos.hilog","hostModuleName":"entry"}]},"moduleSideEffects":true,"originalCode":"export default {}","originalSourcemap":null,"resolvedIds":{},"sourcemapChain":[{"version":3,"file":null,"sources":[null],"sourcesContent":[null],"names":[],"mappings":[[[0,0,0,0],[1,0,0,1],[2,0,0,2],[3,0,0,3],[4,0,0,4],[5,0,0,5],[6,0,0,6],[7,0,0,7],[8,0,0,8],[9,0,0,9],[10,0,0,10],[11,0,0,11],[12,0,0,12],[13,0,0,13],[14,0,0,14],[15,0,0,15],[16,0,0,16]]]}],"syntheticNamedExports":false,"transformDependencies":[],"cacheAst":{"dynamicImportCache":[],"exportAllDeclarationCache":[],"exportNamedDeclarationCache":[],"importCache":[]}}],"plugins":{"watchChangedFiles":{"watchChangedFilesCache":[0,"watchChangedFiles"]},"etsTransform":{"disableCacheOptions":[0,{"bundleName":"com.example.myapplication","entryModuleName":"entry","runtimeOS":"HarmonyOS","resourceTableHash":"790527e39c8c2be7fbbc762f7966104e","etsLoaderVersion":"3.2.12.5"}],"fileCacheInfo":[0,{"/Users/ziyounian/DevEcoStudioProjects/MyApplication/entry/src/main/ets/pages/Index.ets":{"hasEntry":true}}]},"buildInstrument":{"needCoverageInsert":[0,false]},"genAbc":{"is_cache_invalid":[0,false],"ark_compiler_meta_info":[0,"9:9:HarmonyOS:/Users/ziyounian/Library/Huawei/Sdk/openharmony/9/ets/build-tools/ets-loader:3.2.12.5:Release:com.example.myapplication:1043bfc77febe75fafec0c4309faccf1:null_aotCompileMode:null_apPath"]}}}